conn_wizard/__init__.py
conn_wizard/src/__init__.py
conn_wizard/src/connection_manager.py
conn_wizard/src/connection_utility.py
conn_wizard/src/load_connections.py
conn_wizard/test/__init__.py
conn_wizard/test/test.py
ConnKeeper-0.0.10.dist-info/LICENSE
ConnKeeper-0.0.10.dist-info/METADATA
ConnKeeper-0.0.10.dist-info/WHEEL
ConnKeeper-0.0.10.dist-info/top_level.txt
ConnKeeper-0.0.10.dist-info/RECORD
